{
    "avg": {
        "wmc": 10.36,
        "ccn": 6.44,
        "bugs": 0.23,
        "kanDefect": 0.76,
        "relativeSystemComplexity": 140.39,
        "relativeDataComplexity": 2.47,
        "relativeStructuralComplexity": 137.92,
        "volume": 697.64,
        "commentWeight": 34.86,
        "intelligentContent": 73.14,
        "lcom": 2.04,
        "instability": 0.54,
        "afferentCoupling": 1.48,
        "efferentCoupling": 3.24,
        "difficulty": 7.61,
        "mi": 83.08,
        "distance": 0.33,
        "incomingCDep": 3.17,
        "incomingPDep": 1.17,
        "outgoingCDep": 5.33,
        "outgoingPDep": 2.83,
        "classesPerPackage": 4.17
    },
    "sum": {
        "loc": 2423,
        "cloc": 769,
        "lloc": 1657,
        "nbMethods": 123,
        "nbClasses": 25,
        "nbInterfaces": 0,
        "nbPackages": 6,
        "violations": {
            "total": 14,
            "information": 0,
            "warning": 10,
            "error": 4,
            "critical": 0
        }
    }
}